dbSQL_connect/__init__.py
dbSQL_connect/_entry_points.py
dbSQL_connect/_imp.py
dbSQL_connect/importlib_metadata.py
dbSQL_connect/mdurl.py
dbSQL_connect/requires.py
dbSQL_connect-0.1.1.dist-info/METADATA
dbSQL_connect-0.1.1.dist-info/WHEEL
dbSQL_connect-0.1.1.dist-info/top_level.txt
dbSQL_connect-0.1.1.dist-info/RECORD
