Metadata-Version: 2.1
Name: dbSQL-connect
Version: 0.1.1
Summary: This is the simplest module for quick work with files.
Author: virginxlub
Author-email: vzlomka927@yandex.ru
Classifier: Programming Language :: Python :: 3.11
Classifier: License :: OSI Approved :: MIT License
Classifier: Operating System :: OS Independent
Requires-Python: >=3.6
Requires-Dist: requests (>=2.25.1)
